deepnccl/__init__.py
deepnccl-0.0.0.dist-info/METADATA
deepnccl-0.0.0.dist-info/WHEEL
deepnccl-0.0.0.dist-info/top_level.txt
deepnccl-0.0.0.dist-info/RECORD
