Metadata-Version: 2.1
Name: deepnccl
Version: 0.0.0
Summary: deepnccl
Home-page: https://www.aliyun.com
